vods/week4/L04_Exercises/sat_filter/src/rtl/sat_filter.sv
/**
////////////////////////////////////////////////////////////////////////////////////////////////////////////

- Saturation Filter:
  - This module receives a signal and filters it.
  - It can either saturate the output or pass the signal through.

/////////////////////////////////////////////////////////////////////////////////////////////////////////////
*/

module sat_filter #(
    parameter THRESHOLD = 8,  // Threshold value
    parameter DATA_W    = 4   // Data signal bit size
) (
    input  logic              clk,
    input  logic              rst,
    input  logic [DATA_W-1:0] in_data,    // input data signal
    input  logic              in_valid,   // input data valid signal
    output logic              ovf,        // overflow signal
    output logic              out_valid,  // valid output signal
    output logic [DATA_W-1:0] out_data    // output signal
);

  localparam threshold_val = THRESHOLD;

  // Generate dump files because of Icarus.
  initial begin
    $dumpfile("sim_build/sat_filter_waves.vcd");
    $dumpvars(0, sat_filter);
  end

  // Main loop
  always_ff @(posedge clk, posedge rst) begin
    if (rst === 1'b1) begin
      ovf <= 'b0;
      out_valid <= 'b0;
      out_data <= 'b0;
    end else begin
      if (in_valid === 1'b1) begin
        out_valid <= 'b1;
        if (in_data > threshold_val) begin
          out_data <= threshold_val;
          ovf <= 'b1;
        end else begin  // Valid output: (in_data <= threshold_val)
          out_data <= in_data;
          ovf <= 'b0;
        end
      end else begin
        out_valid <= 'b0;
        out_data <= 'b0;
        ovf <= 'b0;
      end
    end
  end

endmodule

vods/week7/L07_Exercise/sat_filter/src/rtl/sat_filter_wrapper.sv
/**
////////////////////////////////////////////////////////////////////////////////////////////////////////////
- Saturation Filter TB

- TB module wrapping the design.

/////////////////////////////////////////////////////////////////////////////////////////////////////////////
*/

// Includes are defined in Makefile when using COCOTB
`ifndef COCOTB_SIM
`include "sat_filter.sv"
`endif

module sat_filter_wrapper #(
    parameter THRESHOLD = 8,  // Threshold value
    parameter DATA_W    = 4   // Data signal bit size
) (
    // input   logic               clk,
    input  logic              rst,
    input  logic [DATA_W-1:0] in_data,    // input data signal
    input  logic              in_valid,   // input data valid signal
    output logic              ovf,        // overflow signal
    output logic              out_valid,  // valid output signal
    output logic [DATA_W-1:0] out_data    // output signal
);

  sat_filter #(
      .THRESHOLD(THRESHOLD),
      .DATA_W(DATA_W)
  ) sat_filter_0 (
      .clk(clk),
      .rst(rst),
      .in_data(in_data),
      .in_valid(in_valid),
      .ovf(ovf),
      .out_valid(out_valid),
      .out_data(out_data)
  );

  // Clock generation
  logic clk;
  initial begin
    clk <= 0;
    forever begin
      #2.5ns clk = ~clk;
    end
  end

endmodule

vods/week6/L06_Exercises/sat_filter/src/tb/sim_build/sat_filter_waves.vcd
$date
	Sun Oct 26 14:40:04 2025
$end
$version
	Icarus Verilog
$end
$timescale
	1ps
$end
$scope module sat_filter_wrapper $end
$scope module sat_filter_0 $end
$var wire 1 ! clk $end
$var wire 4 " in_data [3:0] $end
$var wire 1 # in_valid $end
$var wire 1 $ rst $end
$var parameter 32 % DATA_W $end
$var parameter 32 & THRESHOLD $end
$var parameter 32 ' threshold_val $end
$var reg 4 ( out_data [3:0] $end
$var reg 1 ) out_valid $end
$var reg 1 * ovf $end
$upscope $end
$upscope $end
$scope module sat_filter_wrapper $end
$var wire 4 + in_data [3:0] $end
$var wire 1 # in_valid $end
$var wire 1 $ rst $end
$var wire 1 * ovf $end
$var wire 1 ) out_valid $end
$var wire 4 , out_data [3:0] $end
$var parameter 32 - DATA_W $end
$var parameter 32 . THRESHOLD $end
$var reg 1 ! clk $end
$scope module sat_filter_0 $end
$upscope $end
$upscope $end
$enddefinitions $end
$comment Show the parameter values. $end
$dumpall
b1000 .
b100 -
b1000 '
b1000 &
b100 %
$end
#0
$dumpvars
bx ,
b0 +
x*
x)
bx (
z$
0#
b0 "
0!
$end
#2500
1$
0*
b0 (
b0 ,
0)
1!
#5000
0!
#7500
1!
#10000
0!
#12500
1#
b10 "
b10 +
0$
1!
#15000
0!
#17500
b1111 "
b1111 +
b10 (
b10 ,
1)
1!
#20000
0!
#22500
b1101 "
b1101 +
1*
b1000 (
b1000 ,
1!
#25000
0!
#27500
b1 "
b1 +
1!
#30000
0!
#32500
b1001 "
b1001 +
0*
b1 (
b1 ,
1!
#35000
0!
#37500
b1101 "
b1101 +
1*
b1000 (
b1000 ,
1!
#40000
0!
#42500
b1011 "
b1011 +
1!
#45000
0!
#47500
b11 "
b11 +
1!
#50000
0!
#52500
b1001 "
b1001 +
0*
b11 (
b11 ,
1!
#55000
0!
#57500
b100 "
b100 +
1*
b1000 (
b1000 ,
1!
#60000
0!
#62500
b0 "
b0 +
0*
b100 (
b100 ,
1!
#65000
0!
#67500
b100 "
b100 +
b0 (
b0 ,
1!
#70000
0!
#72500
b1100 "
b1100 +
b100 (
b100 ,
1!
#75000
0!
#77500
b1001 "
b1001 +
1*
b1000 (
b1000 ,
1!
#80000
0!
#82500
b1101 "
b1101 +
1!
#85000
0!
#87500
b1010 "
b1010 +
1!
#90000
0!
#92500
b1 "
b1 +
1!
#95000
0!
#97500
0#
b0 "
b0 +
0*
b1 (
b1 ,
1!
#100000
0!
#102500
b0 (
b0 ,
0)
1!
#105000
0!
#107500
1$
1!
#110000
0!
#112500
1!
#115000
0!
#117500
1#
0$
1!
#120000
0!
#122500
0#
1)
1!
#125000
0!
#127500
1#
b1111 "
b1111 +
0)
1!
#130000
0!
#132500
0#
b0 "
b0 +
1*
b1000 (
b1000 ,
1)
1!
#135000
0!
#137500
1#
b1100 "
b1100 +
0*
b0 (
b0 ,
0)
1!
#140000
0!
#142500
0#
b0 "
b0 +
1*
b1000 (
b1000 ,
1)
1!
#145000
0!
#147500
1#
b1110 "
b1110 +
0*
b0 (
b0 ,
0)
1!
#150000
0!
#152500
0#
b0 "
b0 +
1*
b1000 (
b1000 ,
1)
1!
#155000
0!
#157500
1#
b1001 "
b1001 +
0*
b0 (
b0 ,
0)
1!
#160000
0!
#162500
0#
b0 "
b0 +
1*
b1000 (
b1000 ,
1)
1!
#165000
0!
#167500
0*
b0 (
b0 ,
0)
1!
